rf_monitor.py
setup.py
rf_monitor.egg-info/PKG-INFO
rf_monitor.egg-info/SOURCES.txt
rf_monitor.egg-info/dependency_links.txt
rf_monitor.egg-info/requires.txt
rf_monitor.egg-info/top_level.txt
rfmonitor/__init__.py
rfmonitor/cli.py
rfmonitor/cli_monitor.py
rfmonitor/constants.py
rfmonitor/dialog_about.py
rfmonitor/dialog_gps.py
rfmonitor/dialog_push.py
rfmonitor/dialog_spectrum.py
rfmonitor/dialog_timeline.py
rfmonitor/events.py
rfmonitor/file.py
rfmonitor/gps.py
rfmonitor/gui.py
rfmonitor/legend.py
rfmonitor/monitor.py
rfmonitor/navigation_toolbar.py
rfmonitor/panel_monitor.py
rfmonitor/push.py
rfmonitor/receive.py
rfmonitor/server.py
rfmonitor/settings.py
rfmonitor/signals.py
rfmonitor/toolbar.py
rfmonitor/utils_cli.py
rfmonitor/utils_ui.py
rfmonitor/utils_wx.py
rfmonitor/version.py
rfmonitor/widget_meter.py
rfmonitor/xrchandlers.py
rfmonitor/ui/DialogAbout.xrc
rfmonitor/ui/DialogGps.xrc
rfmonitor/ui/DialogPush.xrc
rfmonitor/ui/DialogSpectrum.xrc
rfmonitor/ui/DialogTimeline.xrc
rfmonitor/ui/FrameMain.xrc
rfmonitor/ui/PanelMonitor.xrc
rfmonitor/ui/__init__.py
rfmonitor/ui/__init__.pyc
rfmonitor/ui/alert.wav
rfmonitor/ui/logo.png