Metadata-Version: 1.1
Name: rf-monitor
Version: 1.0.2
Summary: RF signal monitor
Home-page: https://eartoearoak.com/software/rf-monitor
Author: Al Brown
Author-email: al [at] eartoearok.com
License: GPLv3
Keywords: rf signal monitor
Platform: UNKNOWN
Classifier: Development Status :: 4 - Beta
Classifier: License :: OSI Approved :: GNU General Public License v3 (GPLv3)
Classifier: Operating System :: MacOS :: MacOS X
Classifier: Operating System :: Microsoft :: Windows
Classifier: Operating System :: POSIX :: Linux
Classifier: Programming Language :: Python :: 2.7
Classifier: Topic :: Communications :: Ham Radio
Classifier: Topic :: Scientific/Engineering
Classifier: Topic :: Scientific/Engineering :: Visualization
